{"id":"420","days":"2","hours":"01","minutes":"55","epicentername":"石川県能登地方","latitude":"37°22.0’N","longitude":"137°04.5’E","depth":"10km","magnitude":"4.1","int":{"能登町宇出津":"2.0","穴水町大町＊":"1.9","輪島市河井町＊":"1.8","輪島市鳳至町":"1.7","七尾市能登島向田町＊":"1.6","珠洲市大谷町＊":"1.5","珠洲市正院町＊":"1.4","輪島市舳倉島":"1.3","珠洲市三崎町":"1.2","七尾市本府中町":"1.2","小松市小馬出町":"1.0","志賀町富来領家町":"0.9","七尾市垣吉町＊":"0.9","加賀市大聖寺南町＊":"0.9","白山市別宮町＊":"0.9","七尾市袖ヶ江町＊":"0.8","宝達志水町子浦＊":"0.8","志賀町末吉千古＊":"0.6","能美市来丸町＊":"0.6","中能登町能登部下＊":"0.5","白山市鶴来本町＊":"0.5","富山市新桜町＊":"1.1","氷見市加納＊":"0.9","小矢部市泉町":"0.8","高岡市伏木":"0.7","射水市本町＊":"0.6","南砺市上平細島＊":"0.5","南砺市下梨＊":"0.5"},"dbid":"20240102015542","tags":["202401"]}